{"cameraMode":{"drawMode":0,"name":"Shaded","section":"Shading Mode"},"sceneLighting":true,"audioPlay":false,"sceneViewState":{"m_AlwaysRefresh":false,"showFog":true,"showSkybox":false,"showFlares":true,"showImageEffects":true,"showParticleSystems":true,"showVisualEffectGraphs":true,"m_FxEnabled":true},"in2DMode":false,"pivot":{"x":-0.6579174995422363,"y":2.034773826599121,"z":1.2220096588134766},"rotation":{"x":-0.17123517394065858,"y":0.7833954095840454,"z":-0.24646708369255067,"w":-0.5442708730697632},"size":3.542027711868286,"orthographic":false}